daveloop.py
daveloop_swebench.py
daveloop-1.4.0.dist-info/METADATA
daveloop-1.4.0.dist-info/WHEEL
daveloop-1.4.0.dist-info/entry_points.txt
daveloop-1.4.0.dist-info/top_level.txt
daveloop-1.4.0.dist-info/RECORD
